pycryptax/__init__.py
pycryptax/__main__.py
pycryptax/csvdata.py
pycryptax/datemap.py
pycryptax/gains.py
pycryptax/income.py
pycryptax/output.py
pycryptax/prices.py
pycryptax/util.py
PyCryptax-1.0.0.dist-info/LICENSE
PyCryptax-1.0.0.dist-info/METADATA
PyCryptax-1.0.0.dist-info/WHEEL
PyCryptax-1.0.0.dist-info/entry_points.txt
PyCryptax-1.0.0.dist-info/top_level.txt
PyCryptax-1.0.0.dist-info/RECORD
