Metadata-Version: 2.1
Name: PyCryptax
Version: 1.0.0
Summary: UK Income and Capital Gains Tax Calculator for Cryptocurrencies
Home-page: https://github.com/MatthewLM/PyCryptax
Author: Matthew Mitchell
Author-email: pycryptax@thelibertyportal.com
License: MIT
Platform: UNKNOWN
Classifier: Programming Language :: Python :: 3
Classifier: License :: OSI Approved :: MIT License
Classifier: Operating System :: POSIX
Classifier: Topic :: Office/Business :: Financial :: Accounting
Classifier: Intended Audience :: End Users/Desktop
Classifier: Natural Language :: English
Classifier: Environment :: Console
